stm_metro_client/__init__.py
stm_metro_client/stm_metro_client.py
stm_metro_client-0.0.5.dist-info/DESCRIPTION.rst
stm_metro_client-0.0.5.dist-info/METADATA
stm_metro_client-0.0.5.dist-info/RECORD
stm_metro_client-0.0.5.dist-info/WHEEL
stm_metro_client-0.0.5.dist-info/metadata.json
stm_metro_client-0.0.5.dist-info/top_level.txt
